kreate/kore/__init__.py
kreate/kore/_app.py
kreate/kore/_cli.py
kreate/kore/_core.py
kreate/kore/_jinyaml.py
kreate/kore/_komp.py
kreate/kore/_konfig.py
kreate/kore/_kontext.py
kreate/kore/_kore.py
kreate/kore/_repo.py
kreate/kore/deepchain.py
kreate/kore/dotenv.py
kreate/kore/trace.py
kreate/krypt/__init__.py
kreate/krypt/_krypt.py
kreate/krypt/krypt_functions.py
kreate/kube/__init__.py
kreate/kube/__main__.py
kreate/kube/_kube.py
kreate/kube/_kust.py
kreate/kube/framework/README.md
kreate/kube/framework/define-commands.konf
kreate/kube/framework/define-naming.konf
kreate/kube/framework/init-app.konf
kreate/kube/framework/init-kreate-kube-framework.konf
kreate/kube/framework/init-kubeconfig.konf
kreate/kube/framework/repo-kreate-kube-templates.konf
kreate/kube/patch.py
kreate/kube/resource.py
kreate/kube/templates/README.md
kreate/kube/templates/doc/Deployment.md
kreate/kube/templates/doc/Ingress.md
kreate/kube/templates/doc/Service.md
kreate/kube/templates/kubeconfig/kreate-kubeconfig.konf
kreate/kube/templates/kubeconfig/kubeconfig-template.yaml
kreate/kube/templates/kubernetes/ConfigMap.yaml
kreate/kube/templates/kubernetes/CronJob.yaml
kreate/kube/templates/kubernetes/Deployment.yaml
kreate/kube/templates/kubernetes/Egress.yaml
kreate/kube/templates/kubernetes/HorizontalPodAutoscaler.yaml
kreate/kube/templates/kubernetes/Ingress.yaml
kreate/kube/templates/kubernetes/PodDisruptionBudget.yaml
kreate/kube/templates/kubernetes/Secret.yaml
kreate/kube/templates/kubernetes/SecretBasicAuth.yaml
kreate/kube/templates/kubernetes/Service.yaml
kreate/kube/templates/kubernetes/ServiceMonitor.yaml
kreate/kube/templates/kubernetes/StatefulSet.yaml
kreate/kube/templates/kubernetes/kubernetes-defaults.konf
kreate/kube/templates/kubernetes/kubernetes-templates.konf
kreate/kube/templates/kustomize/AntiAffinity.yaml
kreate/kube/templates/kustomize/EgressLabels.yaml
kreate/kube/templates/kustomize/EgressLabelsCronJob.yaml
kreate/kube/templates/kustomize/HttpProbes.yaml
kreate_kube-1.8.3.dist-info/METADATA
kreate_kube-1.8.3.dist-info/WHEEL
kreate_kube-1.8.3.dist-info/entry_points.txt
kreate_kube-1.8.3.dist-info/licenses/LICENSE
kreate_kube-1.8.3.dist-info/RECORD
