Metadata-Version: 2.1
Name: kreate-kube
Version: 1.8.3
Summary: kreate kubernetes application from templates
Author-Email: Mark Hooijkaas <mark@hooijkaas.net>
Classifier: Programming Language :: Python :: 3
Classifier: License :: OSI Approved :: MIT License
Classifier: Operating System :: OS Independent
Project-URL: Homepage, https://github.com/MarkHooijkaas/kreate-kube
Project-URL: Bug tracker, https://github.com/MarkHooijkaas/kreate-kube/issues
Requires-Python: >=3.8
Requires-Dist: ruamel.yaml
Requires-Dist: jinja2
Requires-Dist: cryptography
Requires-Dist: requests>=2.31.0
Requires-Dist: packaging>=23.2
